LICENSE
MANIFEST.in
README.rst
setup.py
campos/__init__.py
campos/core.py
campos/enums.py
campos/fields.py
campos/forms.py
campos/utils.py
campos/validators.py
campos.egg-info/PKG-INFO
campos.egg-info/SOURCES.txt
campos.egg-info/dependency_links.txt
campos.egg-info/requires.txt
campos.egg-info/top_level.txt
campos/sources/__init__.py
campos/sources/object.py
campos/sources/sqlalchemy.py
docs/building_forms.rst
docs/conf.py
docs/generating_forms.rst
docs/index.rst
docs/installation.rst
docs/make.bat
docs/quickstart.rst
docs/_build/doctrees/building_forms.doctree
docs/_build/doctrees/environment.pickle
docs/_build/doctrees/generating_forms.doctree
docs/_build/doctrees/index.doctree
docs/_build/doctrees/installation.doctree
docs/_build/doctrees/quickstart.doctree
docs/_build/doctrees/api/campos.core.doctree
docs/_build/doctrees/api/campos.doctree
docs/_build/doctrees/api/campos.enums.doctree
docs/_build/doctrees/api/campos.fields.doctree
docs/_build/doctrees/api/campos.forms.doctree
docs/_build/doctrees/api/campos.sources.doctree
docs/_build/doctrees/api/campos.validators.doctree
docs/_build/html/.buildinfo
docs/_build/html/building_forms.html
docs/_build/html/generating_forms.html
docs/_build/html/genindex.html
docs/_build/html/index.html
docs/_build/html/installation.html
docs/_build/html/objects.inv
docs/_build/html/py-modindex.html
docs/_build/html/quickstart.html
docs/_build/html/search.html
docs/_build/html/searchindex.js
docs/_build/html/_images/building.png
docs/_build/html/_images/generating_creation.png
docs/_build/html/_images/generating_creation_mod.png
docs/_build/html/_images/generating_edition.png
docs/_build/html/_images/generating_edition_mod.png
docs/_build/html/_modules/campos.html
docs/_build/html/_modules/index.html
docs/_build/html/_modules/campos/core.html
docs/_build/html/_modules/campos/enums.html
docs/_build/html/_modules/campos/fields.html
docs/_build/html/_modules/campos/forms.html
docs/_build/html/_modules/campos/sources.html
docs/_build/html/_modules/campos/validators.html
docs/_build/html/_modules/campos/sources/object.html
docs/_build/html/_modules/campos/sources/sqlalchemy.html
