Metadata-Version: 1.1
Name: campos
Version: 1.0.1
Summary: Helps you to quickly create and generate fully functional forms
Home-page: https://github.com/jbermudezcabrera/campos
Author: Juan Manuel Bermúdez Cabrera
Author-email: jbermudezcabrera@gmail.com
License: MIT
Download-URL: http://pypi.python.org/pypi/campos
Platform: OS Independent
Classifier: Development Status :: 5 - Production/Stable
Classifier: Environment :: X11 Applications :: Qt
Classifier: Environment :: Win32 (MS Windows)
Classifier: Intended Audience :: Developers
Classifier: License :: OSI Approved :: MIT License
Classifier: Operating System :: OS Independent
Classifier: Programming Language :: Python :: 3
Classifier: Programming Language :: Python :: 3.3
Classifier: Programming Language :: Python :: 3.4
Classifier: Programming Language :: Python :: 3.5
